mplm_sim/__init__.py
mplm_sim/executor.py
mplm_sim/loader.py
mplm_sim/utils.py
mplm_sim-0.1.0.dist-info/LICENSE
mplm_sim-0.1.0.dist-info/METADATA
mplm_sim-0.1.0.dist-info/WHEEL
mplm_sim-0.1.0.dist-info/entry_points.txt
mplm_sim-0.1.0.dist-info/top_level.txt
mplm_sim-0.1.0.dist-info/RECORD
