Metadata-Version: 2.1
Name: mplm-sim
Version: 0.1.0
Summary: mPLM-Sim: Better Cross-Lingual Similarity and Transfer in Multilingual Pretrained Language Models
Home-page: https://github.com/cisnlp/mplm_sim
Author: Peiqin Lin, Chengzhi Hu
Author-email: lpq29743@gmail.com, Chengzhi.Hu@campus.lmu.de
License: Apache Software License 2.0
Keywords: mplm_sim
Platform: UNKNOWN
Classifier: Development Status :: 2 - Pre-Alpha
Classifier: Intended Audience :: Developers
Classifier: License :: OSI Approved :: Apache Software License
Classifier: Natural Language :: English
Classifier: Programming Language :: Python :: 3
Classifier: Programming Language :: Python :: 3.6
Classifier: Programming Language :: Python :: 3.7
Classifier: Programming Language :: Python :: 3.8
Requires-Python: >=3.6
Requires-Dist: Click (>=7.0)
